README.rst
setup.py
xenoglossia/__init__.py
xenoglossia/builtins.py
xenoglossia/decorators.py
xenoglossia/main.py
xenoglossia/xenoglossia.py
xenoglossia.egg-info/PKG-INFO
xenoglossia.egg-info/SOURCES.txt
xenoglossia.egg-info/dependency_links.txt
xenoglossia.egg-info/entry_points.txt
xenoglossia.egg-info/pbr.json
xenoglossia.egg-info/requires.txt
xenoglossia.egg-info/top_level.txt