Metadata-Version: 1.0
Name: xenoglossia
Version: 0.2
Summary: Robust(?) string manipulation language
Home-page: UNKNOWN
Author: Misty De Meo
Author-email: mistydemeo@gmail.com
License: kindest
Platform: UNKNOWN
